yfiles_jupyter_graphs/__init__.py
yfiles_jupyter_graphs/_frontend.py
yfiles_jupyter_graphs/_version.py
yfiles_jupyter_graphs/apply_mappings.py
yfiles_jupyter_graphs/utils.py
yfiles_jupyter_graphs/widget.py
yfiles_jupyter_graphs/graph/__init__.py
yfiles_jupyter_graphs/graph/factories.py
yfiles_jupyter_graphs/graph/importer.py
yfiles_jupyter_graphs/graph/interfaces.py
yfiles_jupyter_graphs/labextension/package.json
yfiles_jupyter_graphs/labextension/static/066daca850d8ffbef007.png
yfiles_jupyter_graphs/labextension/static/165.3364319a56043af5093a.js
yfiles_jupyter_graphs/labextension/static/1dbbe9d028e292f36fcb.png
yfiles_jupyter_graphs/labextension/static/206.9eb06147fe9981ef46b2.js
yfiles_jupyter_graphs/labextension/static/237.2cfc96cb8b90f372648b.js
yfiles_jupyter_graphs/labextension/static/274.a8a0203d2840b652b2ac.js
yfiles_jupyter_graphs/labextension/static/372.fcbf361e48d339e4f2ba.js
yfiles_jupyter_graphs/labextension/static/481.bb483edbe18d70de28f4.js
yfiles_jupyter_graphs/labextension/static/509.0a346415e342aff9b5e4.js
yfiles_jupyter_graphs/labextension/static/574c3a5cca85f4114085.png
yfiles_jupyter_graphs/labextension/static/689.f1ca2c40d156af73f6a8.js
yfiles_jupyter_graphs/labextension/static/739.0a08e6bf2c21c9c410c5.js
yfiles_jupyter_graphs/labextension/static/743.180d76c929f4d814cb84.js
yfiles_jupyter_graphs/labextension/static/893.1f3c04eca941cceed718.js
yfiles_jupyter_graphs/labextension/static/remoteEntry.e035960c28f74844cfe0.js
yfiles_jupyter_graphs/labextension/static/style.js
yfiles_jupyter_graphs/labextension/static/third-party-licenses.json
yfiles_jupyter_graphs/layout/__init__.py
yfiles_jupyter_graphs/layout/configurations.py
yfiles_jupyter_graphs/layout/factories.py
yfiles_jupyter_graphs/layout/interfaces.py
yfiles_jupyter_graphs/nbextension/extension.js
yfiles_jupyter_graphs/nbextension/index.js
yfiles_jupyter_graphs-1.10.9.data/data/share/jupyter/labextensions/yfiles-jupyter-graphs/package.json
yfiles_jupyter_graphs-1.10.9.dist-info/METADATA
yfiles_jupyter_graphs-1.10.9.dist-info/WHEEL
yfiles_jupyter_graphs-1.10.9.dist-info/licenses/LICENSE.md
yfiles_jupyter_graphs-1.10.9.dist-info/RECORD
