Metadata-Version: 2.4
Name: yfiles_jupyter_graphs
Version: 1.10.9
Summary: A diagram visualization extension for JupyterLab and Jupyter Notebooks powered by yFiles for HTML
Project-URL: Homepage, https://www.yworks.com/products/yfiles-graphs-for-jupyter
Project-URL: License, https://github.com/yWorks/yfiles-jupyter-graphs/blob/main/LICENSE.md
Project-URL: Bug Tracker, https://github.com/yWorks/yfiles-jupyter-graphs/issues
Project-URL: Documentation, https://yworks.github.io/yfiles-jupyter-graphs/
Author-email: yWorks Support Team <yfileshtml@yworks.com>
License: # yWorks GmbH - yFiles Graphs for Jupyter Free License
License-File: LICENSE.md
Keywords: Jupyter,JupyterLab,JupyterLab3,diagrams,graph,ipython,visualization,widgets,yfiles
Classifier: Development Status :: 5 - Production/Stable
Classifier: Framework :: Jupyter
Classifier: Framework :: Jupyter :: JupyterLab
Classifier: Framework :: Jupyter :: JupyterLab :: 3
Classifier: Framework :: Jupyter :: JupyterLab :: 4
Classifier: Framework :: Jupyter :: JupyterLab :: Extensions
Classifier: Framework :: Jupyter :: JupyterLab :: Extensions :: Prebuilt
Classifier: Intended Audience :: Developers
Classifier: Intended Audience :: Science/Research
Classifier: Programming Language :: Python
Classifier: Programming Language :: Python :: 3
Classifier: Programming Language :: Python :: 3.6
Classifier: Programming Language :: Python :: 3.7
Classifier: Programming Language :: Python :: 3.8
Classifier: Programming Language :: Python :: 3.9
Classifier: Programming Language :: Python :: 3.10
Classifier: Programming Language :: Python :: 3.11
Classifier: Programming Language :: Python :: 3.12
Classifier: Programming Language :: Python :: 3.13
Classifier: Programming Language :: Python :: 3.14
Classifier: Topic :: Multimedia :: Graphics
Requires-Python: >=3.6
Requires-Dist: ipywidgets>=7.6.0
